itranslit/__init__.py
itranslit/config.py
itranslit/transliterate.py
itranslit/utils.py
itranslit-1.0.2.dist-info/METADATA
itranslit-1.0.2.dist-info/WHEEL
itranslit-1.0.2.dist-info/top_level.txt
itranslit-1.0.2.dist-info/RECORD
