Metadata-Version: 2.1
Name: itranslit
Version: 1.0.2
Summary: iTRANSLIT is a deep learning based transliteration package for indic language
Home-page: https://github.com/sagorbrur/itranslit
Author: Sagor Sarker
Author-email: sagorhem3532@gmail.com
License: MIT
Platform: UNKNOWN
Classifier: Programming Language :: Python :: 3
Classifier: License :: OSI Approved :: MIT License
Classifier: Operating System :: OS Independent
Requires-Python: >=3.6
Requires-Dist: numpy
Requires-Dist: wasabi
Requires-Dist: requests
